{
  "title": "经济型模压胶",
  "subtitle": "产品介绍",
  "images": [
    {
      "src": "/images/products/cn/SiliRub-Economic-Molding/economicSiliconeRubberMolding.png",
      "alt": "economicSiliconeRubberMolding"
    }
  ],
  "sections": [
    {
      "title": "主要特征",
      "content": [
        {
          "type": "features",
          "data": [
            "良好的加工性能"
          ]
        }
      ]
    },
    {
      "title": "主要技术指标",
      "content": [
        {
          "type": "table",
          "data": {
            "rows": [
              [
                {
                  "tag": "th",
                  "text": "项目",
                  "colspan": 1,
                  "rowspan": 1
                },
                {
                  "tag": "th",
                  "text": "NE-5140",
                  "colspan": 1,
                  "rowspan": 1
                },
                {
                  "tag": "th",
                  "text": "NE-5150",
                  "colspan": 1,
                  "rowspan": 1
                },
                {
                  "tag": "th",
                  "text": "NE-5160",
                  "colspan": 1,
                  "rowspan": 1
                },
                {
                  "tag": "th",
                  "text": "NE-5170",
                  "colspan": 1,
                  "rowspan": 1
                },
                {
                  "tag": "th",
                  "text": "NE-5180",
                  "colspan": 1,
                  "rowspan": 1
                },
                {
                  "tag": "th",
                  "text": "测试标准",
                  "colspan": 1,
                  "rowspan": 1
                }
              ],
              [
                {
                  "tag": "td",
                  "text": "外观",
                  "colspan": 1,
                  "rowspan": 1
                },
                {
                  "tag": "td",
                  "text": "乳白色、半透明，无明显杂质",
                  "colspan": 5,
                  "rowspan": 1
                },
                {
                  "tag": "td",
                  "text": "目视检测",
                  "colspan": 1,
                  "rowspan": 1
                }
              ],
              [
                {
                  "tag": "td",
                  "text": "密度, g/cm³",
                  "colspan": 1,
                  "rowspan": 1
                },
                {
                  "tag": "td",
                  "text": "1.10~1.14",
                  "colspan": 1,
                  "rowspan": 1
                },
                {
                  "tag": "td",
                  "text": "1.13~1.17",
                  "colspan": 1,
                  "rowspan": 1
                },
                {
                  "tag": "td",
                  "text": "1.16~1.20",
                  "colspan": 1,
                  "rowspan": 1
                },
                {
                  "tag": "td",
                  "text": "1.19~1.23",
                  "colspan": 1,
                  "rowspan": 1
                },
                {
                  "tag": "td",
                  "text": "1.20~1.24",
                  "colspan": 1,
                  "rowspan": 1
                },
                {
                  "tag": "td",
                  "text": "ASTM D792",
                  "colspan": 1,
                  "rowspan": 1
                }
              ],
              [
                {
                  "tag": "td",
                  "text": "硬度，邵氏A",
                  "colspan": 1,
                  "rowspan": 1
                },
                {
                  "tag": "td",
                  "text": "40±2",
                  "colspan": 1,
                  "rowspan": 1
                },
                {
                  "tag": "td",
                  "text": "50±2",
                  "colspan": 1,
                  "rowspan": 1
                },
                {
                  "tag": "td",
                  "text": "60±2",
                  "colspan": 1,
                  "rowspan": 1
                },
                {
                  "tag": "td",
                  "text": "70±2",
                  "colspan": 1,
                  "rowspan": 1
                },
                {
                  "tag": "td",
                  "text": "80±2",
                  "colspan": 1,
                  "rowspan": 1
                },
                {
                  "tag": "td",
                  "text": "ASTM D2240",
                  "colspan": 1,
                  "rowspan": 1
                }
              ],
              [
                {
                  "tag": "td",
                  "text": "拉伸强度, MPa ≥",
                  "colspan": 1,
                  "rowspan": 1
                },
                {
                  "tag": "td",
                  "text": "6.5",
                  "colspan": 1,
                  "rowspan": 1
                },
                {
                  "tag": "td",
                  "text": "7.0",
                  "colspan": 2,
                  "rowspan": 1
                },
                {
                  "tag": "td",
                  "text": "6.5",
                  "colspan": 1,
                  "rowspan": 1
                },
                {
                  "tag": "td",
                  "text": "6.0",
                  "colspan": 1,
                  "rowspan": 1
                },
                {
                  "tag": "td",
                  "text": "ASTM D412",
                  "colspan": 1,
                  "rowspan": 3
                }
              ],
              [
                {
                  "tag": "td",
                  "text": "断裂伸长率, % ≥",
                  "colspan": 1,
                  "rowspan": 1
                },
                {
                  "tag": "td",
                  "text": "420",
                  "colspan": 1,
                  "rowspan": 1
                },
                {
                  "tag": "td",
                  "text": "320",
                  "colspan": 1,
                  "rowspan": 1
                },
                {
                  "tag": "td",
                  "text": "280",
                  "colspan": 1,
                  "rowspan": 1
                },
                {
                  "tag": "td",
                  "text": "200",
                  "colspan": 1,
                  "rowspan": 1
                },
                {
                  "tag": "td",
                  "text": "150",
                  "colspan": 1,
                  "rowspan": 1
                }
              ],
              [
                {
                  "tag": "td",
                  "text": "拉伸永久变形, % ≤",
                  "colspan": 1,
                  "rowspan": 1
                },
                {
                  "tag": "td",
                  "text": "8",
                  "colspan": 4,
                  "rowspan": 1
                },
                {
                  "tag": "td",
                  "text": "6",
                  "colspan": 1,
                  "rowspan": 1
                }
              ],
              [
                {
                  "tag": "td",
                  "text": "撕裂强度B型 kN/m ≥",
                  "colspan": 1,
                  "rowspan": 1
                },
                {
                  "tag": "td",
                  "text": "16",
                  "colspan": 1,
                  "rowspan": 1
                },
                {
                  "tag": "td",
                  "text": "18",
                  "colspan": 2,
                  "rowspan": 1
                },
                {
                  "tag": "td",
                  "text": "16",
                  "colspan": 2,
                  "rowspan": 1
                },
                {
                  "tag": "td",
                  "text": "ASTM D624",
                  "colspan": 1,
                  "rowspan": 1
                }
              ],
              [
                {
                  "tag": "td",
                  "text": "压缩永久变形, 180℃*22h % ≤",
                  "colspan": 1,
                  "rowspan": 1
                },
                {
                  "tag": "td",
                  "text": "40",
                  "colspan": 1,
                  "rowspan": 1
                },
                {
                  "tag": "td",
                  "text": "35",
                  "colspan": 2,
                  "rowspan": 1
                },
                {
                  "tag": "td",
                  "text": "30",
                  "colspan": 2,
                  "rowspan": 1
                },
                {
                  "tag": "td",
                  "text": "ASTM D395",
                  "colspan": 1,
                  "rowspan": 1
                }
              ],
              [
                {
                  "tag": "td",
                  "text": "回弹性, % ≥",
                  "colspan": 1,
                  "rowspan": 1
                },
                {
                  "tag": "td",
                  "text": "60",
                  "colspan": 1,
                  "rowspan": 1
                },
                {
                  "tag": "td",
                  "text": "50",
                  "colspan": 2,
                  "rowspan": 1
                },
                {
                  "tag": "td",
                  "text": "45",
                  "colspan": 2,
                  "rowspan": 1
                },
                {
                  "tag": "td",
                  "text": "/",
                  "colspan": 1,
                  "rowspan": 1
                }
              ]
            ]
          }
        }
      ]
    }
  ],
  "footnotes": [
    "● 上述物性数据仅供参考。",
    "● 参考固化条件：175℃ × 5min。",
    "● 交联剂用量：2,5-二甲基-2,5-二(叔丁基过氧基)己烷，加入量为 0.65%。",
    "● 随货的检测报告仅是质检部依据公司硫化条件与检测⽅法测试所得；由于硫化条件与检测⽅法的不同，我们不能保证双⽅能得到同样的测试结果，建议使⽤者以⾃⼰的检测条件下得出的检测数据作为使⽤性能参考；以上任何性能数据以及适⽤建议，只是对公司产品使⽤性能的⼀个使⽤参考，⽽不是公司产品在特定应⽤下的有效性或通⽤性的担保"
  ]
}
